grpc_tools/__init__.py
grpc_tools/_protoc_compiler.cpython-310-aarch64-linux-gnu.so
grpc_tools/command.py
grpc_tools/grpc_version.py
grpc_tools/protoc.py
grpc_tools/python_version.py
grpc_tools/_proto/google/protobuf/any.proto
grpc_tools/_proto/google/protobuf/api.proto
grpc_tools/_proto/google/protobuf/descriptor.proto
grpc_tools/_proto/google/protobuf/duration.proto
grpc_tools/_proto/google/protobuf/empty.proto
grpc_tools/_proto/google/protobuf/field_mask.proto
grpc_tools/_proto/google/protobuf/source_context.proto
grpc_tools/_proto/google/protobuf/struct.proto
grpc_tools/_proto/google/protobuf/timestamp.proto
grpc_tools/_proto/google/protobuf/type.proto
grpc_tools/_proto/google/protobuf/wrappers.proto
grpc_tools/_proto/google/protobuf/compiler/plugin.proto
grpcio_tools-1.76.0.dist-info/METADATA
grpcio_tools-1.76.0.dist-info/WHEEL
grpcio_tools-1.76.0.dist-info/entry_points.txt
grpcio_tools-1.76.0.dist-info/top_level.txt
grpcio_tools-1.76.0.dist-info/RECORD
