Metadata-Version: 2.1
Name: grpcio-tools
Version: 1.76.0
Summary: Protobuf code generator for gRPC
Home-page: https://grpc.io
Author: The gRPC Authors
Author-email: grpc-io@googlegroups.com
License: Apache License 2.0
Project-URL: Source Code, https://github.com/grpc/grpc/tree/master/tools/distrib/python/grpcio_tools
Project-URL: Bug Tracker, https://github.com/grpc/grpc/issues
Classifier: Development Status :: 5 - Production/Stable
Classifier: Programming Language :: Python
Classifier: Programming Language :: Python :: 3
Classifier: License :: OSI Approved :: Apache Software License
Requires-Python: >=3.9
Requires-Dist: protobuf <7.0.0,>=6.31.1
Requires-Dist: grpcio >=1.76.0
Requires-Dist: setuptools
